isodatetime/__init__.py
isodatetime/data.py
isodatetime/dumpers.py
isodatetime/parser_spec.py
isodatetime/parsers.py
isodatetime/tests.py
isodatetime/timezone.py
isodatetime/util.py
isodatetime-2018.11.0.dist-info/DESCRIPTION.rst
isodatetime-2018.11.0.dist-info/METADATA
isodatetime-2018.11.0.dist-info/RECORD
isodatetime-2018.11.0.dist-info/WHEEL
isodatetime-2018.11.0.dist-info/metadata.json
isodatetime-2018.11.0.dist-info/top_level.txt
